tes.py
lazylib.egg-info/PKG-INFO
lazylib.egg-info/SOURCES.txt
lazylib.egg-info/dependency_links.txt
lazylib.egg-info/top_level.txt