Metadata-Version: 1.0
Name: lazylib
Version: 0.2
Summary: util for build apps architecture.
Home-page: UNKNOWN
Author: Mikhail Pozdnyakov
Author-email: pozdnyakoffblog@gmail.com
License: UNKNOWN
Platform: UNKNOWN
